odoo/addons/server_config_environment/LICENSE
odoo/addons/server_config_environment/README.rst
odoo/addons/server_config_environment/__init__.py
odoo/addons/server_config_environment/__manifest__.py
odoo/addons/server_config_environment/data/data.xml
odoo/addons/server_config_environment/images/screen.png
odoo/addons/server_config_environment/models/__init__.py
odoo/addons/server_config_environment/models/server_config_environment.py
odoo/addons/server_config_environment/security/ir.model.access.csv
odoo/addons/server_config_environment/security/security.xml
odoo/addons/server_config_environment/static/description/icon.png
odoo/addons/server_config_environment/static/description/index.html
odoo/addons/server_config_environment/views/server_config_environment_views.xml
odoo_addon_server_config_environment-18.0.1.0.0.1.dist-info/METADATA
odoo_addon_server_config_environment-18.0.1.0.0.1.dist-info/WHEEL
odoo_addon_server_config_environment-18.0.1.0.0.1.dist-info/top_level.txt
odoo_addon_server_config_environment-18.0.1.0.0.1.dist-info/RECORD
